iot_manager/Client.py
iot_manager/DeviceType.py
iot_manager/Manager.py
iot_manager/Message.py
iot_manager/Packet.py
iot_manager/ReservedBytes.py
iot_manager/__init__.py
iot_manager/__main__.py
iot_manager-0.0.35.dist-info/METADATA
iot_manager-0.0.35.dist-info/WHEEL
iot_manager-0.0.35.dist-info/top_level.txt
iot_manager-0.0.35.dist-info/RECORD
