Metadata-Version: 2.1
Name: iot-manager
Version: 0.0.35
Summary: A management API for connecting and managing Clients via TCP Sockets
Home-page: https://github.com/dylancrockett/iot-manager
Author: Dylan Crockett
Author-email: dylanrcrockett@gmail.com
License: MIT
Project-URL: Documentation, https://iotmanager.readthedocs.io/
Project-URL: Source Code, https://github.com/dylancrockett/iot-manager
Platform: UNKNOWN
Classifier: Programming Language :: Python :: 3
Classifier: License :: OSI Approved :: MIT License
Classifier: Operating System :: OS Independent
Requires-Python: >=3.6
